{
	"basics": {
		"name": "James Ward",
		"label": "Software Engineer",
		"email": "james@notjam.es",
		"website": "https://notjam.es",
		"location": {
			"city": "New York City",
			"region": "New York",
			"countryCode": "US"
		},
		"profiles": [
			{
				"network": "Github",
				"username": "imnotjames",
				"url": "https://github.com/imnotjames/"
			}
		],
		"summary": "I am an Engineer through and through - I solve practical problems. I get things done, ship amazing software, and create a superb user experience - all while hitting every specification and business requirement.  Unit tests, end to end testing, and test driven development are my go-to tools for crafting solid code in a multitude of languages.\n\nThis isn't just a day job to me, it's a passion."
	},
	"work": [
		{
			"company": "Stealth Seed Stage Startup",
			"position": "Technical Cofounder",
			"startDate": "2020-02-01",
			"summary": "Bringing a product to fruition, starting at nothing."
		}
		{
			"company": "Venmo",
			"position": "Senior Engineering Manager",
			"website": "https://venmo.com/",
			"startDate": "2018-10-01",
			"endDate": "2019-12-01",
			"summary": "Organized the Platform as a Service team - developing the mission, vision, capabilities, and roadmap to encourage a high performing team with a strong sense of ownership.",
			"highlights": [
				"Provide technical leadership to bring reliability of team systems from 90% reliability to 99.999%.",
				"Develop cross-functional initiatives to improve data flow between products to encourage a migration towards distributed architecture."
			]
		},
		{
			"company": "Forkbombus Labs",
			"position": "Co-Founder",
			"website": "https://forkbomb.us",
			"startDate": "2015-11-15",
			"endDate": "2018-09-01",
			"summary": "Understanding the human element behind threats to manage the risks they pose.",
			"highlights": [
				"Built scalable platform with Node.js, Kafka, Tensorflow, PostgreSQL, and ElasticSearch.",
				"Design and implement user experience and workflows of the flagship product.",
				"Produce a full marketing website - from creating wireframes, to generating copy text, to writing the Javascript and HTML."
			]
		},
		{
			"company": "Wayfair",
			"position": "Senior Engineering Manager",
			"website": "https://wayfair.com",
			"startDate": "2014-02-17",
			"endDate": "2017-02-15",
			"summary": "Lead a diverse team of engineers to develop services for scalable, customizable, and personalized interactions with customers.",
			"highlights": [
				"Architect a cross-team platform that generates over 18% of company revenue by enabling open communication with millions of active customers.",
				"Use Kafka, Storm, and HBase to ingest and act upon a large throughput of data through user definable rule sets.",
				"Extensively utilize multiple frontend frameworks to create highly interactive user experiences."
			]
		},
		{
			"company": "Limestone Networks",
			"position": "Software Engineer",
			"website": "https://limestonenetworks.com",
			"startDate": "2012-04-24",
			"endDate": "2014-02-07",
			"summary": "Refactored large portions of legacy codebases to implement new features.",
			"highlights": [
				"Create tooling for NOC automation and Denial of Service mitigation.",
				"Write end-to-end and unit tests to reduce breakage during refactor."
			]
		},
		{
			"company": "Accrisoft",
			"position": "Software Architect",
			"website": "https://accrisoft.com",
			"startDate": "2011-02-11",
			"endDate": "2012-04-04",
			"summary": "Designed and implemented new features, bug fixes, and reduced the memory footprint of the flagship product.",
			"highlights": [
				"Optimize web stack on application servers, reducing infrastructure costs.",
				"Integrate the product with several third-party SOAP and REST APIs."
			]
		}
	],
	"skills": [
		{
			"name": "Java",
			"level": "Advanced",
			"keywords": [
				"Spring",
				"Hibernate",
				"Dropwizard",
				"Storm",
				"Spark"
			]
		},
		{
			"name": "PHP",
			"level": "Expert",
			"keywords": [
				"Laravel",
				"Symfony",
				"Extension Development"
			]
		},
		{
			"name": "SQL",
			"level": "Expert",
			"keywords": [
				"MySQL",
				"T-SQL",
				"PostgreSQL"
			]
		},
		{
			"name": "Cobol",
			"level": "Beginner",
			"keywords": [
				"COBOL-85"
			]
		},
		{
			"name": "Pascal",
			"level": "Intermediate",
			"keywords": [
				"Delphi"
			]
		},
		{
			"name": "Python",
			"level": "Expert",
			"keywords": [
				"Django",
				"Twisted",
				"Pandas",
				"Keras",
				"Tornado",
				"Celery",
				"Heron"
			]
		},
		{
			"name": "Infrastructure",
			"level": "Advanced",
			"keywords": [
				"Linux",
				"Windows",
				"Chef",
				"Kubernetes",
				"Docker",
				"Helm"
			]
		},
		{
			"name": "Javascript",
			"level": "Advanced",
			"keywords": [
				"ES.Next",
				"nodeJS",
				"Express",
				"Tensorflow.js",
				"React",
				"Redux"
			]
		},
		{
			"name": "NoSQL",
			"level": "Intermediate",
			"keywords": [
				"HBase",
				"MongoDB",
				"DynamoDB",
				"Redis",
				"DynamoDB",
				"Cassandra"
			]
		},
		{
			"name": "HTML",
			"level": "Expert",
			"keywords": [
				"HTML5",
				"XHTML",
				"mustache"
			]
		},
		{
			"name": "CSS",
			"level": "Expert",
			"keywords": [
				"CSS3",
				"SASS",
				"LESS",
				"Responsive Design"
			]
		},
		{
			"name": "Perl",
			"level": "Intermediate",
			"keywords": [
				"Mojolicious",
				"CGI"
			]
		},
		{
			"name": "C++",
			"level": "Intermediate",
			"keywords": [
				"Boost"
			]			
		},
		{
			"name": "C",
			"level": "Intermediate",
			"keywords": [
				"C11",
				"C99",
				"CMake"
			]
		},
		{
			"name": "R",
			"level": "Intermediate",
			"keywords": []
		}

	],
	"languages":[
		{
			"language": "English",
			"fluency": "Fluent?"
  		}
  	]
}
